metalfinder/__init__.py
metalfinder/__main__.py
metalfinder/cli.py
metalfinder/concerts.py
metalfinder/output.py
metalfinder/scan.py
metalfinder/api/bandsintown.py
metalfinder-2.1.6.dist-info/entry_points.txt
metalfinder-2.1.6.dist-info/LICENSE
metalfinder-2.1.6.dist-info/WHEEL
metalfinder-2.1.6.dist-info/METADATA
metalfinder-2.1.6.dist-info/RECORD
