Metadata-Version: 2.1
Name: metalfinder
Version: 2.1.6
Summary: scan a music directory to find concerts near a specified location
Author-email: Louis-Philippe Véronneau <pollo@debian.org>
Classifier: License :: OSI Approved :: GNU General Public License v3 or later (GPLv3+)
Classifier: Topic :: Multimedia :: Sound/Audio
Requires-Dist: flit_core >=3.7.1
Requires-Dist: requests >=2.27
Requires-Dist: mutagen
Requires-Dist: feedgenerator
Requires-Dist: packaging
Requires-Dist: docutils ; extra == "doc"
Requires-Dist: pytest ; extra == "test"
Project-URL: Home, https://gitlab.com/baldurmen/metalfinder
Provides-Extra: doc
Provides-Extra: test
